matchingproblems/__init__.py
matchingproblems/generator/__init__.py
matchingproblems/generator/enums.py
matchingproblems/generator/generator.py
matchingproblems/generator/generator_ha_sm_hr.py
matchingproblems/generator/generator_shared.py
matchingproblems/generator/generator_spa.py
matchingproblems/generator/instance_options_parser.py
matchingproblems/solver/__init__.py
matchingproblems/solver/brute_force_solver.py
matchingproblems/solver/enums.py
matchingproblems/solver/fileIO.py
matchingproblems/solver/lp_solver.py
matchingproblems/solver/model.py
matchingproblems/solver/options_parser.py
matchingproblems/solver/solver.py
test/__init__.py
test/brute_force_solver_test.py
test/generator_ha_sm_hr_test.py
test/generator_shared_test.py
test/generator_spa_test.py
test/instance_options_parser_test.py
test/model_test.py
test/options_parser_test.py
matchingproblems-1.4.dist-info/LICENSE.txt
matchingproblems-1.4.dist-info/METADATA
matchingproblems-1.4.dist-info/WHEEL
matchingproblems-1.4.dist-info/top_level.txt
matchingproblems-1.4.dist-info/RECORD
