Metadata-Version: 2.2
Name: matchingproblems
Version: 1.4
Summary: A matching problem generator and solver.
Home-page: http://github.com/fmcooper/matchingproblems
Author: Frances Cooper
Author-email: fmcooper234@gmail.com
License: MIT
Requires-Python: >=3.12
License-File: LICENSE.txt
Requires-Dist: numpy==1.26.4
Requires-Dist: pulp==2.9.0
Dynamic: author
Dynamic: author-email
Dynamic: description
Dynamic: description-content-type
Dynamic: home-page
Dynamic: license
Dynamic: requires-dist
Dynamic: requires-python
Dynamic: summary
